docx_translator/__init__.py
docx_translator/__main__.py
docx_translator/cli.py
docx_translator/streamlit_app.py
docx_translator/translator.py
docx_translator-0.2.1.dist-info/LICENSE
docx_translator-0.2.1.dist-info/METADATA
docx_translator-0.2.1.dist-info/WHEEL
docx_translator-0.2.1.dist-info/entry_points.txt
docx_translator-0.2.1.dist-info/top_level.txt
docx_translator-0.2.1.dist-info/RECORD
