Metadata-Version: 2.1
Name: docx_translator
Version: 0.2.1
Summary: 🌍📄✨ Immersive translation of Word docx files
Author-email: John Dope <hi@zxh.cool>
Project-URL: Homepage, https://github.com/john-theo/docx-translator
Project-URL: Bug Tracker, https://github.com/john-theo/docx-translator/issues
Classifier: Programming Language :: Python :: 3
Classifier: License :: OSI Approved :: MIT License
Classifier: Operating System :: OS Independent
Requires-Python: >=3.9
License-File: LICENSE
Requires-Dist: loguru>=0.7.3
Requires-Dist: openai>=1.76.2
Requires-Dist: python-docx>=1.1.2
Requires-Dist: python-dotenv>=1.1.0
Requires-Dist: requests>=2.32.3
Requires-Dist: streamlit<1.29.0,>=1.24.0
Requires-Dist: tqdm>=4.67.1
Requires-Dist: typer>=0.15.3
Requires-Dist: watchdog>=6.0.0
